tinytoolslib/__init__.py
tinytoolslib/__version__.py
tinytoolslib/constants.py
tinytoolslib/discovery.py
tinytoolslib/exceptions.py
tinytoolslib/flash.py
tinytoolslib/models.py
tinytoolslib/parsers.py
tinytoolslib/requests.py
tinytoolslib-0.5.0.dist-info/METADATA
tinytoolslib-0.5.0.dist-info/WHEEL
tinytoolslib-0.5.0.dist-info/top_level.txt
tinytoolslib-0.5.0.dist-info/RECORD
