Metadata-Version: 2.4
Name: tinytoolslib
Version: 0.5.0
Summary: Set of tools for use with Tinycontrol devices like LK2.X, LK3.X, LK4.X or tcPDU.
Author-email: Bartek Barszczewski <tinycontrol.software@gmail.com>
License-Expression: Apache-2.0
Keywords: tinycontrol,lk,tcpdu
Classifier: Programming Language :: Python :: 3
Classifier: Operating System :: OS Independent
Requires-Python: >=3.7
Requires-Dist: aiohttp<4,>=3.9.3
Requires-Dist: netifaces<1,>=0.11.0
Requires-Dist: requests<3,>=2.31.0
Requires-Dist: tftpy<1,>=0.8.2
